alphabot/__init__.py
alphabot/battery.py
alphabot/camera.py
alphabot/motor.py
alphabot_interface-0.2.5.dist-info/licenses/LICENSE.md
alphabot_interface-0.2.5.dist-info/METADATA
alphabot_interface-0.2.5.dist-info/WHEEL
alphabot_interface-0.2.5.dist-info/top_level.txt
alphabot_interface-0.2.5.dist-info/RECORD
