Metadata-Version: 2.4
Name: alphabot-interface
Version: 0.2.5
Summary: Interface for the Alphabot sensors and camera
Author-email: Sadra <s.s.moosavi.lar@student.tue.nl>
License: MIT
Project-URL: Homepage, https://git.phys.tue.nl/robots/2025-aies-htrbt
Requires-Python: >=3.8
License-File: LICENSE.md
Dynamic: license-file
